monobank-api/__init__.py
monobank-api/client.py
monobank-api/errors.py
monobank-api/helpers.py
monobank-api/signature.py
monobank-api/transport.py
monobank_api/__init__.py
monobank_api/client.py
monobank_api/errors.py
monobank_api/helpers.py
monobank_api/signature.py
monobank_api/transport.py
wayforpay/__init__.py
wayforpay/api.py
wayforpay/constants.py
wayforpay/utils.py
wayforpay-client/__init__.py
wayforpay-client/api.py
wayforpay-1.0.1.dist-info/LICENSE
wayforpay-1.0.1.dist-info/METADATA
wayforpay-1.0.1.dist-info/WHEEL
wayforpay-1.0.1.dist-info/top_level.txt
wayforpay-1.0.1.dist-info/RECORD
