Metadata-Version: 2.1
Name: wayforpay
Version: 1.0.1
Summary: WayForPay API wrapper for Python
Home-page: https://github.com/zagran/wayforpay
Author: Serhii Zahranychnyi
Author-email: serhii.z@edicasoft.com
License: UNKNOWN
Platform: UNKNOWN
Classifier: Programming Language :: Python :: 3
Classifier: License :: OSI Approved :: MIT License
Classifier: Operating System :: OS Independent
Requires-Python: >=3.6
